Workbook

Sheet Проект ЗВК Новосілки
A1: Проект ЗВК Новосілки
H2: Ключевые показатели
A3: 1. Приходная часть | H3: Общий оборот | I3: =E6 -> 132000
A4: № | B4: Описание | C4: Категория | D4: Дата | E4: Сумма | F4: Примечание | H4: Общие безналичные расходы | I4: =E12+E17 -> 123885.71
A5: 1 | B5: Авим Констракшн | D5: 46171 | E5: 132000 | H5: Остаток безналичных средств | I5: =I3-I4 -> 8114.29
A6: Итого | E6: =SUM(E5:E5) -> 132000 | H6: Расход на конвертацию (14%) | I6: =I5*0.14 -> 1136.0006
H7: Заработная плата | I7: =E34 -> 45000
A8: 2. Общие безналичные расходы | H8: Прямые наличные расходы | I8: =E27 -> 3380
A9: № | B9: Описание | C9: Категория | D9: Дата | E9: Сумма | F9: Примечание | H9: Прямые наличные расходы всего | I9: =I7+I8 -> 48380
A10: 1 | B10: ФОП Приходько | D10: 46169 | E10: 74468.09 | H10: Прибыль объекта до общих накладных | I10: =I3-I4-I6-I9 -> -41401.711
A11: 2 | B11: Буддвір (ком) | D11: 46171 | E11: 49417.62 | H11: Доля общих накладных | I11: ='Результат'!E3 -> 21328.527
A12: Итого | E12: =SUM(E10:E11) -> 123885.71 | H12: Чистая прибыль | I12: ='Результат'!I3 -> -62730.237
A14: 2.1 Безналичные расходы на основные средства
A15: № | B15: Описание | C15: Категория | D15: Дата | E15: Сумма | F15: Примечание
A16: 1 | E16: 0
A17: Итого | E17: =SUM(E16:E16) -> 0
A19: 3. Прямые наличные расходы объекта
A20: № | B20: Описание | C20: Категория | D20: Дата | E20: Сумма | F20: Примечание
A21: 1 | B21: Виїзд на обєкт | C21: ГСМ на работу механизмов | D21: 45718 | E21: 800
A22: 2 | B22: Друк проектів | C22: Расходные материалы | D22: 45719 | E22: 500
A23: 3 | B23: Ремонт ПК | C23: Ремонт инструмента | D23: 46102 | E23: 400
A24: 4 | B24: Доставка картриджу | C24: Транспортные услуги | D24: 45679 | E24: 80
A25: 5 | B25: ГСМ Віталій | C25: Собственный транспорт | D25: 46012 | E25: 1200
A26: 6 | B26: мишка | C26: Новый инструмент / основные средства | D26: 46056 | E26: 400
A27: Итого | E27: =SUM(E21:E26) -> 3380
A29: 4. Дневник заработной платы
A30: № | B30: Описание | C30: Категория | D30: Дата | E30: Сумма | F30: Примечание
A31: 1 | B31: Оплата ТАНЯ | C31: Бригада 1 | D31: 46023 | E31: 10000
A32: 2 | B32: Оплата Ірина | C32: Бригада 2 | D32: 46023 | E32: 15000
A33: 3 | B33: ГІП | C33: Прораб | D33: 46023 | E33: 20000
A34: Итого | E34: =SUM(E31:E33) -> 45000

Sheet Новосілки ЗВК 1ч
A1: Новосілки ЗВК 1ч
H2: Ключевые показатели
A3: 1. Приходная часть | H3: Общий оборот | I3: =E6 -> 500000
A4: № | B4: Описание | C4: Категория | D4: Дата | E4: Сумма | F4: Примечание | H4: Общие безналичные расходы | I4: =E12+E17 -> 493967.83
A5: 1 | B5: Авим Констракшн (Аванс) | D5: 46178 | E5: 500000 | H5: Остаток безналичных средств | I5: =I3-I4 -> 6032.17
A6: Итого | E6: =SUM(E5:E5) -> 500000 | H6: Расход на конвертацию (14%) | I6: =I5*0.14 -> 844.5038
H7: Заработная плата | I7: =E34 -> 56000
A8: 2. Общие безналичные расходы | H8: Прямые наличные расходы | I8: =E27 -> 6300
A9: № | B9: Описание | C9: Категория | D9: Дата | E9: Сумма | F9: Примечание | H9: Прямые наличные расходы всего | I9: =I7+I8 -> 62300
A10: 1 | B10: Перший дім (ком) | D10: 46164 | E10: 139232.83 | H10: Прибыль объекта до общих накладных | I10: =I3-I4-I6-I9 -> -57112.334
A11: 2 | B11: ЧБТК (ком) | D11: 46188 | E11: 354735 | H11: Доля общих накладных | I11: ='Результат'!E4 -> 80789.873
A12: Итого | E12: =SUM(E10:E11) -> 493967.83 | H12: Чистая прибыль | I12: ='Результат'!I4 -> -137902.21
A14: 2.1 Безналичные расходы на основные средства
A15: № | B15: Описание | C15: Категория | D15: Дата | E15: Сумма | F15: Примечание
A16: 1 | E16: 0
A17: Итого | E17: =SUM(E16:E16) -> 0
A19: 3. Прямые наличные расходы объекта
A20: № | B20: Описание | C20: Категория | D20: Дата | E20: Сумма | F20: Примечание
A21: 1 | B21: Экскаватор | C21: ГСМ на работу механизмов | D21: 45831 | E21: 300
A22: 2 | B22: Шпаклівка | C22: Расходные материалы | D22: 46034 | E22: 400
A23: 3 | B23: Ремонт болгарки | C23: Ремонт инструмента | D23: 46035 | E23: 600
A24: 4 | B24: Доставка | C24: Транспортные услуги | D24: 45668 | E24: 400
A25: 5 | B25: ГСМ Саша | C25: Собственный транспорт | D25: 45669 | E25: 1000
A26: 6 | B26: Гайковерт | C26: Новый инструмент / основные средства | D26: 45698 | E26: 3600
A27: Итого | E27: =SUM(E21:E26) -> 6300
A29: 4. Дневник заработной платы
A30: № | B30: Описание | C30: Категория | D30: Дата | E30: Сумма | F30: Примечание
A31: 1 | B31: Аванс | C31: Бригада 1 | D31: 45689 | E31: 30000
A32: 2 | B32: Розрахунок | C32: Бригада 2 | D32: 46082 | E32: 6000
A33: 3 | B33: ЗП травень | C33: Прораб | D33: 46170 | E33: 20000
A34: Итого | E34: =SUM(E31:E33) -> 56000

Sheet Накладні
A1: ОБЩИЕ НАКЛАДНЫЕ РАСХОДЫ
H2: Сводка
A3: № | B3: Описание | C3: Группа | D3: Категория | E3: Дата | F3: Сумма | H3: Безналичные накладные | I3: =F4+F5+F6+F7+F8+F9+F10+F11+F12 -> 109440
A4: 1 | B4: Аккорд банк ( обслуг рах) | C4: Безналичные | D4: Банк | E4: 46170 | F4: 400 | H4: Корректировка конвертации 14% | I4: =I3*0.14 -> 15321.6
A5: 2 | B5: Аккорд банк ( комісія) | C5: Безналичные | D5: Банк | E5: 46164 | F5: 10 | H5: Наличные накладные | I5: =F13+F14+F15 -> 8000
A6: 3 | B6: Аккорд банк ( комісія) | C6: Безналичные | D6: Банк | E6: 46178 | F6: 20 | H6: Накладные к распределению | I6: =I3+I5-I4 -> 102118.4
A7: 4 | B7: Аккорд банк ( комісія) | C7: Безналичные | D7: Банк | E7: 46188 | F7: 10
A8: 5 | B8: РКО | C8: Безналичные | D8: Банк | E8: 46164 | F8: 100
A9: 6 | B9: Поповнення ПДВ | C9: Безналичные | D9: Налоги | E9: 46177 | F9: 26500
A10: 7 | B10: Поповнення ПДВ | C10: Безналичные | D10: Налоги | E10: 46188 | F10: 22400
A11: 8 | B11: ЗП ФОП ФедосеєваГ.Б. (травень) | C11: Безналичные | D11: Другое | E11: 46178 | F11: 20000
A12: 9 | B12: ЗП ФОП ФедосеєваГ.Б. (березень, квітень) | C12: Безналичные | D12: Другое | E12: 46164 | F12: 40000
A13: 10 | B13: ремонт ТОйота | C13: Наличные | D13: ГСМ и техобслуживание | E13: 46154 | F13: 1400
A14: 11 | B14: Ремонт Принтер | C14: Наличные | D14: Другое | E14: 45923 | F14: 600
A15: 12 | B15: Проживання бригада 1 травень | C15: Наличные | D15: Жильё и аренда | E15: 45801 | F15: 6000
A16: Итого | F16: =SUM(F4:F15) -> 117440

Sheet Результат
A1: СВОДНЫЙ РЕЗУЛЬТАТ ПО ВСЕМ СТРОЙКАМ
A2: № п/п | B2: Наименование | C2: Лист | D2: Общий оборот | E2: Накладные (доля) | F2: Общие безналичные расходы | G2: Расход на конвертацию | H2: Наличные расходы | I2: Чистая прибыль | J2: Процент прибыли
A3: 1 | B3: Проект ЗВК Новосілки | C3: Проект ЗВК Новосілки | D3: ='Проект ЗВК Новосілки'!I3 -> 132000 | E3: =IFERROR($E$5*D3/$D$5,0) -> 21328.527 | F3: ='Проект ЗВК Новосілки'!I4 -> 123885.71 | G3: ='Проект ЗВК Новосілки'!I6 -> 1136.0006 | H3: ='Проект ЗВК Новосілки'!I9 -> 48380 | I3: =D3-E3-F3-G3-H3 -> -62730.237 | J3: =IFERROR(I3/D3,0) -> -0.47522907
A4: 2 | B4: Новосілки ЗВК 1ч | C4: Новосілки ЗВК 1ч | D4: ='Новосілки ЗВК 1ч'!I3 -> 500000 | E4: =IFERROR($E$5*D4/$D$5,0) -> 80789.873 | F4: ='Новосілки ЗВК 1ч'!I4 -> 493967.83 | G4: ='Новосілки ЗВК 1ч'!I6 -> 844.5038 | H4: ='Новосілки ЗВК 1ч'!I9 -> 62300 | I4: =D4-E4-F4-G4-H4 -> -137902.21 | J4: =IFERROR(I4/D4,0) -> -0.27580441
B5: ВСЕГО | D5: =SUM(D3:D4) -> 632000 | E5: ='Накладні'!I6 -> 102118.4 | F5: =SUM(F3:F4) -> 617853.54 | G5: =SUM(G3:G4) -> 1980.5044 | H5: =SUM(H3:H4) -> 110680 | I5: =SUM(I3:I4) -> -200632.44 | J5: =IFERROR(I5/D5,0) -> -0.3174564
B7: Коэффициент общих накладных | C7: =IFERROR(E5/D5,0) -> 0.16157975 | E7: Ставка конвертации | F7: 0.14
